MANIFEST.in
README.md
setup.cfg
setup.py
swampdragon_notifications/__init__.py
swampdragon_notifications/admin.py
swampdragon_notifications/models.py
swampdragon_notifications/notification_connection.py
swampdragon_notifications/notifier.py
swampdragon_notifications/routers.py
swampdragon_notifications/send_mail.py
swampdragon_notifications/subject_processors.py
swampdragon_notifications.egg-info/PKG-INFO
swampdragon_notifications.egg-info/SOURCES.txt
swampdragon_notifications.egg-info/dependency_links.txt
swampdragon_notifications.egg-info/requires.txt
swampdragon_notifications.egg-info/top_level.txt
swampdragon_notifications/backends/__init__.py
swampdragon_notifications/backends/backends.py
swampdragon_notifications/backends/base_backend.py
swampdragon_notifications/backends/email_notifications.py
swampdragon_notifications/backends/realtime_notifications.py
swampdragon_notifications/online/__init__.py
swampdragon_notifications/online/mock_user_manager.py
swampdragon_notifications/online/redis_user_manager.py
swampdragon_notifications/online/user_manager.py
swampdragon_notifications/static/js/index.js
swampdragon_notifications/static/js/package.json
swampdragon_notifications/static/js/dist/swampdragon-notifications.js
swampdragon_notifications/static/js/dist/swampdragon-notifications.min.js
swampdragon_notifications/static/js/src/desktop-notifications.js
swampdragon_notifications/static/js/src/swampdragon-notifications.js
tests/__init__.py
tests/conftest.py
tests/models.py
tests/subject_renderers.py
tests/test_email_notifications.py
tests/test_online_users.py
tests/test_realtime_notifications.py
tests/test_subject_processor.py
tests/urls.py