Metadata-Version: 1.1
Name: swampdragon-notifications
Version: 0.1.3.1
Summary: SwampDragon notifications 
Home-page: https://github.com/jonashagstedt/swampdragon-notifications
Author: Jonas Hagstedt
Author-email: hagstedt@gmail.com
License: BSD
Keywords: Notifications,realtime notifications
Platform: UNKNOWN
Classifier: Development Status :: 4 - Beta
Classifier: License :: OSI Approved :: BSD License
Classifier: Programming Language :: Python :: 2.7
Classifier: Programming Language :: Python :: 3
Classifier: Programming Language :: Python :: 3.3
Classifier: Programming Language :: Python :: 3.4
